MANIFEST.in
README.md
setup.py
pyplantuml/__init__.py
pyplantuml/adapter.py
pyplantuml/cli.py
pyplantuml/online.py
pyplantuml/writer.py
pyplantuml.egg-info/PKG-INFO
pyplantuml.egg-info/SOURCES.txt
pyplantuml.egg-info/dependency_links.txt
pyplantuml.egg-info/entry_points.txt
pyplantuml.egg-info/requires.txt
pyplantuml.egg-info/top_level.txt