Metadata-Version: 1.0
Name: pyplantuml
Version: 0.1.51
Summary: Creates UML diagrams from python source code.
Home-page: https://github.com/cb109/pyplantuml.git
Author: Christoph Buelter
Author-email: buelter.christoph@gmail.com
License: UNKNOWN
Keywords: uml,code analysis,overview,quickstart,diagram,OOP
Platform: UNKNOWN
